finthermos.cpython-37m-darwin.so
finthermos-0.0.1.dist-info/LICENSE
finthermos-0.0.1.dist-info/METADATA
finthermos-0.0.1.dist-info/WHEEL
finthermos-0.0.1.dist-info/top_level.txt
finthermos-0.0.1.dist-info/RECORD
