Metadata-Version: 2.1
Name: finthermos
Version: 0.0.1
Summary: Infrastructure for Finance
Home-page: https://github.com/tbonza/finthermos
Author: Tyler Brown
License: UNKNOWN
Project-URL: Source Code, https://github.com/tbonza/thermos
Platform: UNKNOWN
Classifier: Development Status :: 1 - Planning
Classifier: Intended Audience :: Developers
Classifier: Natural Language :: English
Classifier: Operating System :: MacOS :: MacOS X
Classifier: Operating System :: POSIX :: Linux
Classifier: Programming Language :: Python
Classifier: Programming Language :: Python :: 3.7
License-File: LICENSE
Provides-Extra: test
Requires-Dist: pytest ; extra == 'test'
